engine_cli/__init__.py
engine_cli/cache.py
engine_cli/commands/__init__.py
engine_cli/commands/advanced.py
engine_cli/commands/agent.py
engine_cli/commands/book.py
engine_cli/commands/book_backup.py
engine_cli/commands/config.py
engine_cli/commands/examples.py
engine_cli/commands/monitoring.py
engine_cli/commands/project.py
engine_cli/commands/protocol.py
engine_cli/commands/team.py
engine_cli/commands/tool.py
engine_cli/commands/workflow.py
engine_cli/commands/workflow.py.backup
engine_cli/config.py
engine_cli/formatting.py
engine_cli/interactive.py
engine_cli/main.py
engine_cli/storage/__init__.py
engine_cli/storage/agent_book_storage.py
engine_cli/storage/workflow_state_manager.py
engine_cli-1.1.0.dist-info/METADATA
engine_cli-1.1.0.dist-info/WHEEL
engine_cli-1.1.0.dist-info/entry_points.txt
engine_cli-1.1.0.dist-info/licenses/LICENSE
engine_cli-1.1.0.dist-info/licenses/LICENSE-COMMERCIAL
engine_cli-1.1.0.dist-info/RECORD
