Metadata-Version: 2.4
Name: engine-cli
Version: 1.1.0
Summary: Engine Framework CLI - Command Line Interface for AI Agent Orchestration
License: AGPL-3.0
License-File: LICENSE
License-File: LICENSE-COMMERCIAL
Keywords: cli,ai,agents,orchestration,framework,terminal
Author: Engine Framework Team
Author-email: engine@example.com
Requires-Python: >=3.11,<3.14
Classifier: Development Status :: 5 - Production/Stable
Classifier: Intended Audience :: Developers
Classifier: License :: OSI Approved :: GNU Affero General Public License v3
Classifier: Operating System :: OS Independent
Classifier: Programming Language :: Python :: 3
Classifier: Programming Language :: Python :: 3.11
Classifier: Programming Language :: Python :: 3.12
Classifier: Programming Language :: Python :: 3.13
Classifier: Topic :: Software Development :: Libraries :: Python Modules
Classifier: Topic :: System :: Shells
Classifier: Topic :: Utilities
Requires-Dist: click (>=8.1.7,<9.0.0)
Requires-Dist: engine-core (>=1.0.1,<2.0.0)
Requires-Dist: prompt-toolkit (>=3.0.39,<4.0.0)
Requires-Dist: pydantic (>=2.0.0,<3.0.0)
Requires-Dist: pyyaml (>=6.0.1,<7.0.0)
Requires-Dist: rich (>=12.6.0,<13.0.0)
Project-URL: Homepage, https://github.com/engine-agi/engine-cli
Project-URL: Repository, https://github.com/engine-agi/engine-cli
